Metadata-Version: 2.1
Name: ecssh
Version: 2
Summary: accessing aws ecs instances
Home-page: https://git.osuv.de/m/ecssh
Author: Markus Bergholz
Author-email: markuman@gmail.com  
License: WTFPL
Platform: UNKNOWN
